setup.py
client/__init__.py
client/client.py
client/client/__init__.py
client/client/add_cont.py
client/client/client_db.py
client/client/client_sock.py
client/client/del_cont.py
client/client/main_win.py
client/client/main_window_conv.py
client/client/start_dial.py
client/common/__init__.py
client/common/decorators.py
client/common/descriptors.py
client/common/errors.py
client/common/metaclasses.py
client/common/settings.py
client/common/utils.py
client/logs/__init__.py
client/logs/client_log_config.py
client/logs/server_log_config.py
mess_client_amk.egg-info/PKG-INFO
mess_client_amk.egg-info/SOURCES.txt
mess_client_amk.egg-info/dependency_links.txt
mess_client_amk.egg-info/requires.txt
mess_client_amk.egg-info/top_level.txt